src/alu_module.v
module alu (
    // Inputs to the ALU
    input wire [7:0] a,      // Operand 1
    input wire [7:0] b,      // Operand 2
    input wire [2:0] op,     // Operation Code
    input wire rst,          // System Reset

    // Outputs from the ALU
    output reg [7:0] res,    // Result
    output reg c_out,        // Carry out bit
    output reg zero,         // Zero Flag
    output reg ovf           // Overflow Flag
);

    reg [8:0] temp;          // For intermediate result with carry

    always @(*) begin
        if (rst) begin
            temp   = 9'b0;
            res    <= 8'b0;
            c_out  = 1'b0;
            zero   = 1'b0;
            ovf    = 1'b0;
        end else begin
            case (op)
                3'b000: temp = a & b;           // AND
                3'b001: temp = a | b;           // OR
                3'b010: temp = a ^ b;           // XOR
                3'b011: temp = {1'b0, ~a};      // NOT (only `a` is inverted)
                3'b100: temp = a + b;           // ADD
                3'b101: temp = a - b;           // SUB
                3'b110: temp = a + 1;           // INC
                3'b111: temp = a - 1;           // DEC
                default: temp = 9'b0;
            endcase

            res   = temp[7:0];
            c_out = temp[8];
            zero  = (temp[7:0] == 8'b0);

            // Overflow logic only applies to ADD and SUB
            case (op)
                3'b100: ovf = (a[7] == b[7]) && (res[7] != a[7]); // ADD
                3'b101: ovf = (a[7] != b[7]) && (res[7] != a[7]); // SUB
                default: ovf = 1'b0;
            endcase
        end
    end

endmodule

testbenches/alu_tb.v
`timescale 1ns/1ps

module alu_tb;

    //INPUTS
    reg [7:0] a;
    reg [7:0] b;
    reg [2:0] op;
    reg rst;
    wire [7:0] res;
    wire c_out;
    wire z_flag;
    wire ovf;

    alu utt(
        .a(a),
        .b(b),
        .op(op),
        .rst(rst),
        .res(res),
        .c_out(c_out),
        .zero(z_flag),
        .ovf(ovf)
    );

    task check_result;
        input [7:0] expected;
        input [255:0] msg;
        begin
            #5;
            if(res == expected)
                $display("[PASS] %s => res: %d", msg, res);
            else
                $display("[FAIL] %s => res: %d (expected %d)", msg, res, expected); 
        end
    endtask

    initial begin
        $dumpfile("alu.vcd");
        $dumpvars(0, alu_tb);

        //Resetting setup
        rst = 1;
        a = 8'd0;
        b = 8'd0;
        op = 3'b000;
        #10;
        rst = 0;

        //Testin AND
        a = 8'b11001100; b = 8'b10101010; op = 3'b000;
        check_result(8'b10001000, "AND test");

        // OR
        a = 8'b11001100; b = 8'b10101010; op = 3'b001;
        check_result(8'b11101110, "OR test");

        // XOR
        a = 8'b11001100; b = 8'b10101010; op = 3'b010;
        check_result(8'b01100110, "XOR test");

        // NOT
        a = 8'b00001111; b = 8'b00000000; op = 3'b011;
        check_result(~8'b00001111, "NOT test");

        // ADD with no carry
        a = 8'd50; b = 8'd20; op = 3'b100;
        check_result(8'd70, "ADD no carry");

        // ADD with overflow
        a = 8'd200; b = 8'd100; op = 3'b100;
        check_result(8'd44, "ADD overflow");

        // SUB
        a = 8'd100; b = 8'd40; op = 3'b101;
        check_result(8'd60, "SUB test");

        // INC
        a = 8'd99; b = 8'd0; op = 3'b110;
        check_result(8'd100, "INC test");

        // DEC
        a = 8'd5; b = 8'd0; op = 3'b111;
        check_result(8'd4, "DEC test");

        $display("All Tests Completed");
        $finish;
    end
endmodule

testbenches/alu.vcd
$date
	Mon Jul 14 20:27:00 2025
$end
$version
	Icarus Verilog
$end
$timescale
	1ps
$end
$scope module alu_tb $end
$var wire 1 ! z_flag $end
$var wire 8 " res [7:0] $end
$var wire 1 # ovf $end
$var wire 1 $ c_out $end
$var reg 8 % a [7:0] $end
$var reg 8 & b [7:0] $end
$var reg 3 ' op [2:0] $end
$var reg 1 ( rst $end
$scope module utt $end
$var wire 8 ) a [7:0] $end
$var wire 8 * b [7:0] $end
$var wire 3 + op [2:0] $end
$var wire 1 ( rst $end
$var reg 1 $ c_out $end
$var reg 1 # ovf $end
$var reg 8 , res [7:0] $end
$var reg 9 - temp [8:0] $end
$var reg 1 ! zero $end
$upscope $end
$scope task check_result $end
$var reg 8 . expected [7:0] $end
$var reg 256 / msg [255:0] $end
$upscope $end
$upscope $end
$enddefinitions $end
$comment Show the parameter values. $end
$dumpall
$end
#0
$dumpvars
bx /
bx .
b0 -
b0 ,
b0 +
b0 *
b0 )
1(
b0 '
b0 &
b0 %
0$
0#
b0 "
0!
$end
#10000
b10001000 "
b10001000 ,
b10001000 -
b100000101001110010001000010000001110100011001010111001101110100 /
b10001000 .
b10101010 &
b10101010 *
b11001100 %
b11001100 )
0(
#15000
b11101110 "
b11101110 ,
b11101110 -
b1001111010100100010000001110100011001010111001101110100 /
b11101110 .
b1 '
b1 +
#20000
b1100110 "
b1100110 ,
b1100110 -
b101100001001111010100100010000001110100011001010111001101110100 /
b1100110 .
b10 '
b10 +
#25000
b11110000 "
b11110000 ,
b11110000 -
b100111001001111010101000010000001110100011001010111001101110100 /
b11110000 .
b11 '
b11 +
b0 &
b0 *
b1111 %
b1111 )
#30000
b1000110 "
b1000110 ,
b1000110 -
b10000010100010001000100001000000110111001101111001000000110001101100001011100100111001001111001 /
b1000110 .
b100 '
b100 +
b10100 &
b10100 *
b110010 %
b110010 )
#35000
1$
b101100 "
b101100 ,
b100101100 -
b10000010100010001000100001000000110111101110110011001010111001001100110011011000110111101110111 /
b101100 .
b1100100 &
b1100100 *
b11001000 %
b11001000 )
#40000
0$
b111100 "
b111100 ,
b111100 -
b101001101010101010000100010000001110100011001010111001101110100 /
b111100 .
b101 '
b101 +
b101000 &
b101000 *
b1100100 %
b1100100 )
#45000
b1100100 "
b1100100 ,
b1100100 -
b100100101001110010000110010000001110100011001010111001101110100 /
b1100100 .
b110 '
b110 +
b0 &
b0 *
b1100011 %
b1100011 )
#50000
b100 "
b100 ,
b100 -
b100010001000101010000110010000001110100011001010111001101110100 /
b100 .
b111 '
b111 +
b101 %
b101 )
