src/instruction_decoder.v
module decoder (
    input wire clk,
    input wire sys_rst,

    //From PRAM
    input wire [7:0] instr_byte,
    input wire [7:0] operand1,
    input wire [7:0] operand2,
    input wire cmd_start,

    //From LCD Display
    input wire lcd_done,

    //From Registers
    input wire [7:0] reg_a,
    input wire [7:0] reg_b,
    input wire [7:0] reg_c,
    input wire [7:0] reg_d,
    input wire [7:0] reg_flags,

    //From ALU
    input wire [7:0] res,

    //From SRAM
    input wire [7:0] sram_rd_data,

    //To Program Counter
    output reg pc_hlt,
    output reg jmp_en,
    output reg [8:0] jmp_addr,
    output reg [1:0] instr_size,

    //To SRAM
    output reg [7:0] sram_addr,
    output reg sram_rd_en,
    output reg sram_wr_en,
    output reg [7:0] sram_wr_data,

    //To LCD Driver
    output reg [7:0] lcd_data,
    output reg [7:0] data_loc,
    output reg loc_req,
    output reg strt,

    //To Register Block
    output reg [7:0] reg_wr_data,
    output reg [1:0] reg_wr_addr,
    output reg reg_wr_en,

    //To ALU
    output reg [2:0] alu_inst,
    output reg [7:0] op_1,
    output reg [7:0] op_2,
    output reg alu_en
);
    localparam STATE_INIT           = 3'd0;
    localparam STATE_FETCH          = 3'd1;
    localparam STATE_RETRIEVE       = 3'd2;
    localparam STATE_DECODE         = 3'd3;
    localparam STATE_EXECUTE_START  = 3'd4;
    localparam STATE_EXECUTE_END    = 3'd5;

    reg [2:0] state;

    always @(posedge clk or posedge sys_rst) begin
        if (sys_rst) begin
            state <= STATE_INIT;
            pc_hlt <= 0;
            sram_rd_en <= 0;
            sram_wr_en <= 0;
            reg_wr_en <= 0;
            instr_size <= 1;
        end else begin
            case (state)
                STATE_INIT: begin
                    pc_hlt <= 0;
                    sram_rd_en <= 0;
                    sram_wr_en <= 0;
                    reg_wr_en <= 0;
                    if(cmd_start) begin
                        state <= STATE_FETCH;                        
                    end
                    else begin
                        state <= STATE_INIT;
                    end
                end
                STATE_FETCH: begin
                    case (instr_byte[7:4])
                        4'b0000: state <= STATE_DECODE;
                        4'b0001: state <= STATE_DECODE;
                        4'b0010: state <= STATE_RETRIEVE;
                        4'b0011: state <= STATE_DECODE;
                        4'b1000: state <= STATE_DECODE;
                        4'b1001: state <= STATE_DECODE;
                        4'b1010: state <= STATE_DECODE;
                        4'b1011: state <= STATE_DECODE;
                        4'b1100: state <= STATE_DECODE;
                        4'b1101: state <= STATE_DECODE;
                        4'b1110: state <= STATE_DECODE;
                        4'b1111: state <= STATE_DECODE;
                        default: state <= STATE_INIT;
                    endcase
                end

                STATE_RETRIEVE: begin
                    if (instr_byte[7:4] == 4'b0010) begin
                        sram_addr <= operand1;
                        sram_rd_en <= 1;
                    end
                    state <= STATE_DECODE;
                end

                STATE_DECODE: begin
                    case (instr_byte[7:4])
                        4'b0000: begin // MOV R1, R2
                            reg_wr_addr <= instr_byte[3:2];
                            case (instr_byte[1:0])
                                2'b00: reg_wr_data <= reg_a;
                                2'b01: reg_wr_data <= reg_b;
                                2'b10: reg_wr_data <= reg_c;
                                2'b11: reg_wr_data <= reg_d;
                            endcase
                            instr_size <= 1;
                            state <= STATE_EXECUTE_START;
                        end
                        4'b0001: begin // MOV R, IMM
                            reg_wr_addr <= instr_byte[3:2];
                            reg_wr_data <= operand1;
                            instr_size <= 2;
                            state <= STATE_EXECUTE_START;
                        end
                        4'b0010: begin // MOV R, [ADDR]
                            reg_wr_en <= 1;
                            reg_wr_addr <= instr_byte[3:2];
                            reg_wr_data <= sram_rd_data;
                            instr_size <= 2;
                            state <= STATE_EXECUTE_START;
                        end
                        4'b0011: begin // MOV [ADDR], R
                            sram_addr <= operand1;
                            sram_wr_en <= 1;
                            case (instr_byte[3:2])
                                2'b00: sram_wr_data <= reg_a;
                                2'b01: sram_wr_data <= reg_b;
                                2'b10: sram_wr_data <= reg_c;
                                2'b11: sram_wr_data <= reg_d;
                            endcase
                            instr_size <= 2;
                            state <= STATE_EXECUTE_START;
                        end
                        4'b1000: begin  //AND R1, R2
                            alu_inst <= 3'b000;
                            case (instr_byte[3:2])
                                2'b00: op_1 <= reg_a;
                                2'b01: op_1 <= reg_b;
                                2'b10: op_1 <= reg_c;
                                2'b11: op_1 <= reg_d;
                            endcase
                            case (instr_byte[1:0])
                                2'b00: op_2 <= reg_a;
                                2'b01: op_2 <= reg_b;
                                2'b10: op_2 <= reg_c;
                                2'b11: op_2 <= reg_d;
                            endcase
                        end
                        4'b1001: begin  //OR R1, R2
                            alu_inst <= 3'b001;
                            case (instr_byte[3:2])
                                2'b00: op_1 <= reg_a;
                                2'b01: op_1 <= reg_b;
                                2'b10: op_1 <= reg_c;
                                2'b11: op_1 <= reg_d;
                            endcase
                            case (instr_byte[1:0])
                                2'b00: op_2 <= reg_a;
                                2'b01: op_2 <= reg_b;
                                2'b10: op_2 <= reg_c;
                                2'b11: op_2 <= reg_d;
                            endcase
                        end
                        4'b1010: begin  //XOR R1, R2
                            alu_inst <= 3'b010;
                            case (instr_byte[3:2])
                                2'b00: op_1 <= reg_a;
                                2'b01: op_1 <= reg_b;
                                2'b10: op_1 <= reg_c;
                                2'b11: op_1 <= reg_d;
                            endcase
                            case (instr_byte[1:0])
                                2'b00: op_2 <= reg_a;
                                2'b01: op_2 <= reg_b;
                                2'b10: op_2 <= reg_c;
                                2'b11: op_2 <= reg_d;
                            endcase
                        end
                        4'b1011: begin  //NOT R1
                            alu_inst <= 3'b011;
                            case (instr_byte[3:2])
                                2'b00: op_1 <= reg_a;
                                2'b01: op_1 <= reg_b;
                                2'b10: op_1 <= reg_c;
                                2'b11: op_1 <= reg_d;
                            endcase
                        end
                        4'b1100: begin  //ADD R1, R2
                            alu_inst <= 3'b100;
                            case (instr_byte[3:2])
                                2'b00: op_1 <= reg_a;
                                2'b01: op_1 <= reg_b;
                                2'b10: op_1 <= reg_c;
                                2'b11: op_1 <= reg_d;
                            endcase
                            case (instr_byte[3:2])
                                2'b00: op_2 <= reg_a;
                                2'b01: op_2 <= reg_b;
                                2'b10: op_2 <= reg_c;
                                2'b11: op_2 <= reg_d;
                            endcase
                        end
                        4'b1101: begin  //SUB R1, R2
                            alu_inst <= 3'b101;
                            case (instr_byte[3:2])
                                2'b00: op_1 <= reg_a;
                                2'b01: op_1 <= reg_b;
                                2'b10: op_1 <= reg_c;
                                2'b11: op_1 <= reg_d;
                            endcase
                            case (instr_byte[3:2])
                                2'b00: op_2 <= reg_a;
                                2'b01: op_2 <= reg_b;
                                2'b10: op_2 <= reg_c;
                                2'b11: op_2 <= reg_d;
                            endcase
                        end
                        4'b1101: begin  //INC R1
                            alu_inst <= 3'b110;
                            case (instr_byte[3:2])
                                2'b00: op_1 <= reg_a;
                                2'b01: op_1 <= reg_b;
                                2'b10: op_1 <= reg_c;
                                2'b11: op_1 <= reg_d;
                            endcase
                        end
                        4'b1111: begin  //DEC R1
                            alu_inst <= 3'b1111;
                            case (instr_byte[3:2])
                                2'b00: op_1 <= reg_a;
                                2'b01: op_1 <= reg_b;
                                2'b10: op_1 <= reg_c;
                                2'b11: op_1 <= reg_d;
                            endcase
                        end
                    endcase
                end

                STATE_EXECUTE_START: begin
                    case (instr_byte[7:4])
                        4'b0000: begin   // MOV R1, R2
                            reg_wr_en <= 1;
                        end

                        4'b0001: begin  // MOV R, IMM
                            reg_wr_en <= 1;
                        end

                        4'b0010: begin  // MOV R, [ADDR]
                            reg_wr_en <= 1;
                        end

                        4'b0011: begin  // MOV [ADDR], R
                            sram_wr_en <= 1;
                        end

                        4'b1000: begin  // AND R1, R2
                            alu_en <= 1;
                        end
                        4'b1001: begin  // OR R1, R2
                            alu_en <= 1;
                        end
                        4'b1010: begin  // XOR R1, R2
                            alu_en <= 1;
                        end
                        4'b1011: begin  // NOT R
                            alu_en <= 1;
                        end
                        4'b1100: begin  // ADD R1, R2
                            alu_en <= 1;
                        end
                        4'b1101: begin  // SUB R1, R2
                            alu_en <= 1;
                        end
                        4'b1110: begin  // INC R
                            alu_en <= 1;
                        end
                        4'b1111: begin  // DEC R
                            alu_en <= 1;
                        end
                        
                    endcase
                    state <= STATE_EXECUTE_END;
                end

                STATE_EXECUTE_END: begin
                    case (instr_byte[7:4])
                        4'b0000: begin  // MOV R1, R2
                            reg_wr_en <= 0;
                        end

                        4'b0001: begin  // MOV R, IMM
                            reg_wr_en <= 0;
                        end

                        4'b0010: begin  // MOV R, [ADDR]
                            reg_wr_en <= 0;
                        end

                        4'b1000: begin  // AND R1, R2
                            alu_en <= 0;
                        end
                        4'b1001: begin  // OR R1, R2
                            alu_en <= 0;
                        end
                        4'b1010: begin  // XOR R1, R2
                            alu_en <= 0;
                        end
                        4'b1011: begin  // NOT R
                            alu_en <= 0;
                        end
                        4'b1100: begin  // ADD R1, R2
                            alu_en <= 0;
                        end
                        4'b1101: begin  // SUB R1, R2
                            alu_en <= 0;
                        end
                        4'b1110: begin  // INC R
                            alu_en <= 0;
                        end
                        4'b1111: begin  // DEC R
                            alu_en <= 0;
                        end
                    endcase
                    state <= STATE_INIT;
                end
            endcase
        end
    end

endmodule

testbenches/decoder_tb.v
`timescale 1ns/1ns

module decoder_tb;

    // Inputs
    reg clk;
    reg sys_rst;
    reg [7:0] instr_byte;
    reg [7:0] operand1;
    reg [7:0] operand2;
    reg lcd_done;
    reg [7:0] reg_a, reg_b, reg_c, reg_d, reg_flags;
    reg [7:0] res;
    reg [7:0] sram_data;
    reg pc_strt;

    // Outputs
    wire pc_hlt, jmp_en, sram_rd_en, sram_wr_en, reg_wr_en;
    wire [1:0] instr_size, reg_wr_addr;
    wire [8:0] jmp_addr;
    wire [7:0] sram_addr, lcd_data, data_loc, reg_wr_data, sram_wr_data;
    wire [2:0] alu_inst;
    wire [7:0] op_1, op_2;

    // Instantiate decoder
    decoder uut (
        .clk(clk),
        .sys_rst(sys_rst),
        .instr_byte(instr_byte),
        .operand1(operand1),
        .operand2(operand2),
        .lcd_done(lcd_done),
        .reg_a(reg_a),
        .reg_b(reg_b),
        .reg_c(reg_c),
        .reg_d(reg_d),
        .reg_flags(reg_flags),
        .res(res),
        .sram_rd_data(sram_data),
        .pc_hlt(pc_hlt),
        .jmp_en(jmp_en),
        .jmp_addr(jmp_addr),
        .instr_size(instr_size),
        .sram_addr(sram_addr),
        .sram_rd_en(sram_rd_en),
        .sram_wr_en(sram_wr_en),
        .lcd_data(lcd_data),
        .data_loc(data_loc),
        .sram_wr_data(sram_wr_data),
        .loc_req(),
        .strt(),
        .reg_wr_data(reg_wr_data),
        .reg_wr_addr(reg_wr_addr),
        .reg_wr_en(reg_wr_en),
        .alu_inst(alu_inst),
        .op_1(op_1),
        .op_2(op_2),
        .cmd_start(pc_strt)
    );

    // Clock generation
    always #13 clk = ~clk;

    // Task to check result
    task check;
        input [1023:0] name;
        input condition;
        begin
            if (condition)
                $display("[PASS] %s", name);
            else
                $display("[FAIL] %s", name);
        end
    endtask

    initial begin
        $dumpfile("decoder_tb.vcd");
        $dumpvars(0, decoder_tb);

        // Initial state
        clk = 0;
        pc_strt = 0;
        sys_rst = 1;
        instr_byte = 0;
        operand1 = 0;
        operand2 = 0;
        lcd_done = 0;
        reg_a = 8'h11;
        reg_b = 8'h22;
        reg_c = 8'h33;
        reg_d = 8'h44;
        reg_flags = 0;
        res = 8'hAA;
        sram_data = 8'h00;

        #15 sys_rst = 0;

        // === Test MOV A, B ===
        pc_strt <= 1;
        instr_byte = 8'b00000001; // MOV A, B
        #30; // Wait for FSM to complete execution
        pc_strt <= 0;
        #100;

        check("MOV A, B", reg_wr_addr == 2'b00 && reg_wr_data == 8'h22);

        // === Test MOV D, IMM ===
        instr_byte = 8'h1C;
        pc_strt <= 1;
        #30
        pc_strt <= 0;
        operand1 = 8'h42;
        #100;

        check("MOV A, 0x42", reg_wr_addr == 2'b11 && reg_wr_data == 8'h42);

        // === Test MOV C, [0x51] === //
        pc_strt <= 1;
        #30
        pc_strt <= 0;
        instr_byte = 8'h28;
        operand1 = 8'h51;
        #120;

        check("MOV C, [0x51]", reg_wr_addr == 2'b10 && sram_addr == 8'h51);

        // === Test MOV [0x75], B === //
        pc_strt <= 1;
        #30;
        pc_strt <= 0;
        instr_byte = 8'h34;
        operand1 = 8'h75;
        #120;

        check("MOV [0x51], B", sram_addr == 8'h75 && sram_wr_data == 8'h22);

        // === Test AND A, B === //
        pc_strt = 1;
        #30;
        pc_strt = 0;
        instr_byte = 8'h81;
        #100;
        check("AND A, B", op_1 == 8'h11 && op_2 == 8'h22 && alu_inst == 3'b0);
        
        $display("Test completed.");
        $finish;
    end

endmodule

decoder_tb.vcd
$date
	Tue Jul 15 14:44:05 2025
$end
$version
	Icarus Verilog
$end
$timescale
	1ns
$end
$scope module decoder_tb $end
$var wire 1 ! sram_wr_en $end
$var wire 8 " sram_wr_data [7:0] $end
$var wire 1 # sram_rd_en $end
$var wire 8 $ sram_addr [7:0] $end
$var wire 1 % reg_wr_en $end
$var wire 8 & reg_wr_data [7:0] $end
$var wire 2 ' reg_wr_addr [1:0] $end
$var wire 1 ( pc_hlt $end
$var wire 8 ) op_2 [7:0] $end
$var wire 8 * op_1 [7:0] $end
$var wire 8 + lcd_data [7:0] $end
$var wire 1 , jmp_en $end
$var wire 9 - jmp_addr [8:0] $end
$var wire 2 . instr_size [1:0] $end
$var wire 8 / data_loc [7:0] $end
$var wire 3 0 alu_inst [2:0] $end
$var reg 1 1 clk $end
$var reg 8 2 instr_byte [7:0] $end
$var reg 1 3 lcd_done $end
$var reg 8 4 operand1 [7:0] $end
$var reg 8 5 operand2 [7:0] $end
$var reg 1 6 pc_strt $end
$var reg 8 7 reg_a [7:0] $end
$var reg 8 8 reg_b [7:0] $end
$var reg 8 9 reg_c [7:0] $end
$var reg 8 : reg_d [7:0] $end
$var reg 8 ; reg_flags [7:0] $end
$var reg 8 < res [7:0] $end
$var reg 8 = sram_data [7:0] $end
$var reg 1 > sys_rst $end
$scope module uut $end
$var wire 1 1 clk $end
$var wire 1 6 cmd_start $end
$var wire 8 ? instr_byte [7:0] $end
$var wire 1 3 lcd_done $end
$var wire 8 @ operand1 [7:0] $end
$var wire 8 A operand2 [7:0] $end
$var wire 8 B reg_a [7:0] $end
$var wire 8 C reg_b [7:0] $end
$var wire 8 D reg_c [7:0] $end
$var wire 8 E reg_d [7:0] $end
$var wire 8 F reg_flags [7:0] $end
$var wire 8 G res [7:0] $end
$var wire 8 H sram_rd_data [7:0] $end
$var wire 1 > sys_rst $end
$var parameter 3 I STATE_DECODE $end
$var parameter 3 J STATE_EXECUTE_END $end
$var parameter 3 K STATE_EXECUTE_START $end
$var parameter 3 L STATE_FETCH $end
$var parameter 3 M STATE_INIT $end
$var parameter 3 N STATE_RETRIEVE $end
$var reg 1 O alu_en $end
$var reg 3 P alu_inst [2:0] $end
$var reg 8 Q data_loc [7:0] $end
$var reg 2 R instr_size [1:0] $end
$var reg 9 S jmp_addr [8:0] $end
$var reg 1 , jmp_en $end
$var reg 8 T lcd_data [7:0] $end
$var reg 1 U loc_req $end
$var reg 8 V op_1 [7:0] $end
$var reg 8 W op_2 [7:0] $end
$var reg 1 ( pc_hlt $end
$var reg 2 X reg_wr_addr [1:0] $end
$var reg 8 Y reg_wr_data [7:0] $end
$var reg 1 % reg_wr_en $end
$var reg 8 Z sram_addr [7:0] $end
$var reg 1 # sram_rd_en $end
$var reg 8 [ sram_wr_data [7:0] $end
$var reg 1 ! sram_wr_en $end
$var reg 3 \ state [2:0] $end
$var reg 1 ] strt $end
$upscope $end
$scope task check $end
$var reg 1 ^ condition $end
$var reg 1024 _ name [1023:0] $end
$upscope $end
$upscope $end
$enddefinitions $end
$comment Show the parameter values. $end
$dumpall
b10 N
b0 M
b1 L
b100 K
b101 J
b11 I
$end
#0
$dumpvars
bx _
x^
x]
b0 \
bx [
bx Z
bx Y
bx X
bx W
bx V
xU
bx T
bx S
b1 R
bx Q
bx P
xO
b0 H
b10101010 G
b0 F
b1000100 E
b110011 D
b100010 C
b10001 B
b0 A
b0 @
b0 ?
1>
b0 =
b10101010 <
b0 ;
b1000100 :
b110011 9
b100010 8
b10001 7
06
b0 5
b0 4
03
b0 2
01
bx 0
bx /
b1 .
bx -
x,
bx +
bx *
bx )
0(
bx '
bx &
0%
bx $
0#
bx "
0!
$end
#13
11
#15
16
b1 2
b1 ?
0>
#26
01
#39
b1 \
11
#45
06
#52
01
#65
b11 \
11
#78
01
#91
b100 \
b100010 &
b100010 Y
b0 '
b0 X
11
#104
01
#117
b101 \
1%
11
#130
01
#143
b0 \
0%
11
#145
16
b11100 2
b11100 ?
1^
b100110101001111010101100010000001000001001011000010000001000010 _
#156
01
#169
b1 \
11
#175
06
b1000010 4
b1000010 @
#182
01
#195
b11 \
11
#208
01
#221
b100 \
b10 .
b10 R
b1000010 &
b1000010 Y
b11 '
b11 X
11
#234
01
#247
b101 \
1%
11
#260
01
#273
b0 \
0%
11
#275
16
b100110101001111010101100010000001000001001011000010000000110000011110000011010000110010 _
#286
01
#299
b1 \
11
#305
06
b1010001 4
b1010001 @
b101000 2
b101000 ?
#312
01
#325
b10 \
11
#338
01
#351
b11 \
1#
b1010001 $
b1010001 Z
11
#364
01
#377
b100 \
b0 &
b0 Y
b10 '
b10 X
1%
11
#390
01
#403
b101 \
11
#416
01
#425
16
b1001101010011110101011000100000010000110010110000100000010110110011000001111000001101010011000101011101 _
#429
b0 \
0%
11
#442
01
#455
b1 \
0#
06
11
b1110101 4
b1110101 @
b110100 2
b110100 ?
#468
01
#481
b11 \
11
#494
01
#507
b100 \
b100010 "
b100010 [
1!
b1110101 $
b1110101 Z
11
#520
01
#533
b101 \
11
#546
01
#559
b0 \
0!
11
#572
01
#575
16
b1001101010011110101011000100000010110110011000001111000001101010011000101011101001011000010000001000010 _
#585
b1 \
11
#598
01
#605
b10000001 2
b10000001 ?
06
#611
b11 \
11
#624
01
#637
b100010 )
b100010 W
b10001 *
b10001 V
b0 0
b0 P
11
#650
01
#663
11
#676
01
#689
11
#702
01
#705
b100000101001110010001000010000001000001001011000010000001000010 _
