src/instruction_decoder.v
module decoder (
    //----- INPUTS TO DECODER -----//
    //From System
    input wire clk,
    input wire sys_rst,

    //From PRAM
    input wire [7:0] instr_byte,
    input wire [7:0] operand1,
    input wire [7:0] operand2,

    //From LCD Display
    input wire lcd_done,

    //From Registers
    input wire [7:0] reg_a,
    input wire [7:0] reg_b,
    input wire [7:0] reg_c,
    input wire [7:0] reg_d,
    input wire [7:0] reg_flags,

    //From ALU
    input wire [7:0] res,

    //To and From SRAM
    inout wire [7:0] sram_data,

    //----- OUTPUTS FROM DECODER -----//
    //To Program Counter
    output reg hlt,
    output reg jmp_en,
    output reg [8:0] jmp_addr,
    output reg [1:0] instr_size,

    //To SRAM
    output reg [7:0] sram_addr,
    output reg rd_en,
    output reg wr_en,

    //To LCD Driver
    output reg [7:0] lcd_data,
    output reg [7:0] data_loc,
    output reg loc_req,
    output reg strt,

    //To Register Block
    output reg [7:0] reg_data,
    output reg [1:0] reg_addr,

    //To ALU
    output reg [2:0] alu_inst,
    output reg [7:0] op_1,
    output reg [7:0] op_2
);

    // SRAM Tri-state control
    reg [7:0] sram_data_out;
    reg sram_drive;

    assign sram_data = sram_drive ? sram_data_out : 8'bz;

    // FSM States
    localparam STATE_FETCH     = 3'b000;
    localparam STATE_DECODE    = 3'b001;
    localparam STATE_WAIT_LCD  = 3'b010;
    localparam STATE_HALT      = 3'b011;

    reg [2:0] state;

    always @(posedge clk or posedge sys_rst) begin
        if (sys_rst) begin
            state <= STATE_FETCH;
            hlt <= 0;
            jmp_en <= 0;
            instr_size <= 1;
        end else begin
            case (state)
                STATE_FETCH: begin
                    // Reset control signals
                    hlt <= 0;
                    jmp_en <= 0;
                    alu_inst <= 3'b000;
                    instr_size <= 1;
                    rd_en <= 0;
                    wr_en <= 0;
                    strt <= 0;
                    sram_drive <= 0;

                    state <= STATE_DECODE;
                end

                STATE_DECODE: begin
                    case (instr_byte[7:4])
                        4'b0000: begin // MOV R1, R2
                            reg_addr <= instr_byte[3:2];
                            case (instr_byte[1:0])
                                2'b00: reg_data <= reg_a;
                                2'b01: reg_data <= reg_b;
                                2'b10: reg_data <= reg_c;
                                2'b11: reg_data <= reg_d;
                            endcase
                            instr_size <= 1;
                        end

                        4'b0001: begin // MOV R, IMM
                            reg_addr <= instr_byte[3:2];
                            reg_data <= operand1;
                            instr_size <= 2;
                        end

                        4'b0010: begin // MOV R, [ADDR]
                            reg_addr <= instr_byte[3:2];
                            sram_addr <= operand1;
                            rd_en <= 1;
                            instr_size <= 2;
                        end

                        4'b0011: begin // MOV [ADDR], R
                            sram_addr <= operand1;
                            case (instr_byte[3:2])
                                2'b00: sram_data_out <= reg_a;
                                2'b01: sram_data_out <= reg_b;
                                2'b10: sram_data_out <= reg_c;
                                2'b11: sram_data_out <= reg_d;
                            endcase
                            sram_drive <= 1;
                            wr_en <= 1;
                            instr_size <= 2;
                        end

                        4'b0100: begin // PRNT
                            if (instr_byte[1:0] == 2'b00) begin // PRNT REG
                                case (instr_byte[3:2])
                                    2'b00: lcd_data <= reg_a;
                                    2'b01: lcd_data <= reg_b;
                                    2'b10: lcd_data <= reg_c;
                                    2'b11: lcd_data <= reg_d;
                                endcase
                                strt <= 1;
                                loc_req <= 1;
                                data_loc <= reg_a;
                                state <= STATE_WAIT_LCD;
                            end else begin // PRNT [ADDR]
                                sram_addr <= operand1;
                                rd_en <= 1;
                                loc_req <= 1;
                                data_loc <= reg_a;
                                strt <= 1;
                                state <= STATE_WAIT_LCD;
                            end
                            instr_size <= 2;
                        end

                        4'b0101: begin // Jumps
                            jmp_addr <= operand1;
                            instr_size <= 2;
                            case (instr_byte[3:0])
                                4'b0000: jmp_en <= 1;                      // JMP
                                4'b0001: jmp_en <= reg_flags[0];          // JZ
                                4'b0010: jmp_en <= ~reg_flags[0];         // JNZ
                                4'b0011: jmp_en <= reg_flags[1];          // JOV
                            endcase
                        end

                        4'b0110: begin
                            instr_size <= 1; // NOP
                        end

                        4'b0111: begin
                            if (instr_byte[3:0] == 4'b0000)
                                hlt <= 1; // HLT
                            else if (instr_byte[3:0] == 4'b1111)
                                instr_size <= 3; // WAIT
                        end

                        4'b1000: begin // AND R1, R2
                            alu_inst <= 3'b000;
                            op_1 <= (instr_byte[3:2] == 2'b00) ? reg_a :
                                    (instr_byte[3:2] == 2'b01) ? reg_b :
                                    (instr_byte[3:2] == 2'b10) ? reg_c : reg_d;
                            op_2 <= (instr_byte[1:0] == 2'b00) ? reg_a :
                                    (instr_byte[1:0] == 2'b01) ? reg_b :
                                    (instr_byte[1:0] == 2'b10) ? reg_c : reg_d;
                            reg_addr <= instr_byte[3:2];
                            reg_data <= res;
                            instr_size <= 1;
                        end

                        // TODO: Add other ALU operations like OR, XOR, ADD, SUB, etc.

                    endcase
                    state <= STATE_FETCH;
                end

                STATE_WAIT_LCD: begin
                    if (lcd_done) begin
                        strt <= 0;
                        state <= STATE_FETCH;
                    end
                end

                STATE_HALT: begin
                    hlt <= 1;
                end
            endcase
        end
    end

endmodule

testbenches/decoder_tb.v
`timescale 1ns/1ns

module decoder_tb;

    // Inputs
    reg clk;
    reg sys_rst;
    reg [7:0] instr_byte;
    reg [7:0] operand1;
    reg [7:0] operand2;
    reg lcd_done;
    reg [7:0] reg_a;
    reg [7:0] reg_b;
    reg [7:0] reg_c;
    reg [7:0] reg_d;
    reg [7:0] reg_flags;
    reg [7:0] res;
    wire [7:0] sram_data;

    // Outputs
    wire hlt;
    wire jmp_en;
    wire [8:0] jmp_addr;
    wire [1:0] instr_size;
    wire [7:0] sram_addr;
    wire rd_en;
    wire wr_en;
    wire [7:0] lcd_data;
    wire [7:0] data_loc;
    wire loc_req;
    wire strt;
    wire [7:0] reg_data;
    wire [1:0] reg_addr;
    wire [2:0] alu_inst;
    wire [7:0] op_1;
    wire [7:0] op_2;

    // Assign dummy SRAM data
    assign sram_data = 8'h55;

    // Instantiate the decoder
    decoder uut (
        .clk(clk),
        .sys_rst(sys_rst),
        .instr_byte(instr_byte),
        .operand1(operand1),
        .operand2(operand2),
        .lcd_done(lcd_done),
        .reg_a(reg_a),
        .reg_b(reg_b),
        .reg_c(reg_c),
        .reg_d(reg_d),
        .reg_flags(reg_flags),
        .res(res),
        .sram_data(sram_data),
        .hlt(hlt),
        .jmp_en(jmp_en),
        .jmp_addr(jmp_addr),
        .instr_size(instr_size),
        .sram_addr(sram_addr),
        .rd_en(rd_en),
        .wr_en(wr_en),
        .lcd_data(lcd_data),
        .data_loc(data_loc),
        .loc_req(loc_req),
        .strt(strt),
        .reg_data(reg_data),
        .reg_addr(reg_addr),
        .alu_inst(alu_inst),
        .op_1(op_1),
        .op_2(op_2)
    );

    // Clock generation
    always #5 clk = ~clk;

    // Task to check expected values
    task check;
        input [8*32:1] testname;
        input condition;
        begin
            if (condition)
                $display("[PASS] %s", testname);
            else
                $display("[FAIL] %s", testname);
        end
    endtask

    // Test Sequence
    initial begin
        // VCD dump
        $dumpfile("decoder_tb.vcd");
        $dumpvars(0, decoder_tb);

        // Initial values
        clk = 0;
        sys_rst = 1;
        instr_byte = 8'h00;
        operand1 = 8'h00;
        operand2 = 8'h00;
        lcd_done = 0;
        reg_a = 8'h11;
        reg_b = 8'h22;
        reg_c = 8'h33;
        reg_d = 8'h44;
        reg_flags = 8'b00000000;
        res = 8'hAA;

        // Wait one clock cycle, then release reset
        #10 sys_rst = 0;

        // === Test 1: MOV A, IMM ===
        // Opcode: 0001 00xx => MOV A, IMM
        instr_byte = 8'b00010000; // MOV A, IMM
        operand1 = 8'h42;         // Immediate value
        #50;
        check("MOV A, IMM", reg_data == 8'h42 && reg_addr == 2'b00 && instr_size == 2);

        // === Test 2: MOV B, C ===
        instr_byte = 8'b00000110; // MOV B, C
        #10;
        #10;
        check("MOV B, C", reg_data == 8'h33 && reg_addr == 2'b01);

        // === Test 3: HLT ===
        instr_byte = 8'b01110000; // HLT
        #10;
        #10;
        check("HLT Instruction", hlt == 1'b1);

        // === Test 4: PRNT REG ===
        instr_byte = 8'b01000000; // PRNT A
        #10;
        #10;
        check("PRNT A", lcd_data == 8'h11 && strt == 1);

        $display("All tests completed.");
        $finish;
    end

endmodule

src/decoder_tb.vcd
$date
	Sun Jul 13 21:22:56 2025
$end
$version
	Icarus Verilog
$end
$timescale
	1ns
$end
$scope module decoder_tb $end
$var wire 8 ! sram_data [7:0] $end
$var wire 1 " wr_en $end
$var wire 1 # strt $end
$var wire 8 $ sram_addr [7:0] $end
$var wire 8 % reg_data [7:0] $end
$var wire 2 & reg_addr [1:0] $end
$var wire 1 ' rd_en $end
$var wire 8 ( op_2 [7:0] $end
$var wire 8 ) op_1 [7:0] $end
$var wire 1 * loc_req $end
$var wire 8 + lcd_data [7:0] $end
$var wire 1 , jmp_en $end
$var wire 9 - jmp_addr [8:0] $end
$var wire 2 . instr_size [1:0] $end
$var wire 1 / hlt $end
$var wire 8 0 data_loc [7:0] $end
$var wire 3 1 alu_inst [2:0] $end
$var reg 1 2 clk $end
$var reg 8 3 instr_byte [7:0] $end
$var reg 1 4 lcd_done $end
$var reg 8 5 operand1 [7:0] $end
$var reg 8 6 operand2 [7:0] $end
$var reg 8 7 reg_a [7:0] $end
$var reg 8 8 reg_b [7:0] $end
$var reg 8 9 reg_c [7:0] $end
$var reg 8 : reg_d [7:0] $end
$var reg 8 ; reg_flags [7:0] $end
$var reg 8 < res [7:0] $end
$var reg 1 = sys_rst $end
$scope module uut $end
$var wire 1 2 clk $end
$var wire 8 > instr_byte [7:0] $end
$var wire 1 4 lcd_done $end
$var wire 8 ? operand1 [7:0] $end
$var wire 8 @ operand2 [7:0] $end
$var wire 8 A reg_a [7:0] $end
$var wire 8 B reg_b [7:0] $end
$var wire 8 C reg_c [7:0] $end
$var wire 8 D reg_d [7:0] $end
$var wire 8 E reg_flags [7:0] $end
$var wire 8 F res [7:0] $end
$var wire 8 G sram_data [7:0] $end
$var wire 1 = sys_rst $end
$var parameter 3 H STATE_DECODE $end
$var parameter 3 I STATE_FETCH $end
$var parameter 3 J STATE_HALT $end
$var parameter 3 K STATE_WAIT_LCD $end
$var reg 3 L alu_inst [2:0] $end
$var reg 8 M data_loc [7:0] $end
$var reg 1 / hlt $end
$var reg 2 N instr_size [1:0] $end
$var reg 9 O jmp_addr [8:0] $end
$var reg 1 , jmp_en $end
$var reg 8 P lcd_data [7:0] $end
$var reg 1 * loc_req $end
$var reg 8 Q op_1 [7:0] $end
$var reg 8 R op_2 [7:0] $end
$var reg 1 ' rd_en $end
$var reg 2 S reg_addr [1:0] $end
$var reg 8 T reg_data [7:0] $end
$var reg 8 U sram_addr [7:0] $end
$var reg 8 V sram_data_out [7:0] $end
$var reg 1 W sram_drive $end
$var reg 3 X state [2:0] $end
$var reg 1 # strt $end
$var reg 1 " wr_en $end
$upscope $end
$scope task check $end
$var reg 1 Y condition $end
$var reg 256 Z testname [256:1] $end
$upscope $end
$upscope $end
$enddefinitions $end
$comment Show the parameter values. $end
$dumpall
b10 K
b11 J
b0 I
b1 H
$end
#0
$dumpvars
bx Z
xY
b0 X
xW
bx V
bx U
bx T
bx S
bx R
bx Q
bx P
bx O
b1 N
bx M
bx L
bx G
b10101010 F
b0 E
b1000100 D
b110011 C
b100010 B
b10001 A
b0 @
b0 ?
b0 >
1=
b10101010 <
b0 ;
b1000100 :
b110011 9
b100010 8
b10001 7
b0 6
b0 5
04
b0 3
02
bx 1
bx 0
0/
b1 .
bx -
0,
bx +
x*
bx )
bx (
x'
bx &
bx %
bx $
x#
x"
bx !
$end
#5
12
#10
02
b1000010 5
b1000010 ?
b10000 3
b10000 >
0=
#15
b1010101 !
b1010101 G
b1 X
0W
0#
0"
0'
b0 1
b0 L
12
#20
02
#25
b0 X
b10 .
b10 N
b1000010 %
b1000010 T
b0 &
b0 S
12
#30
02
#35
b1 X
b1 .
b1 N
12
#40
02
#45
b0 X
b10 .
b10 N
12
#50
02
#55
b1 X
b1 .
b1 N
12
#60
02
b110 3
b110 >
0Y
b1001101010011110101011000100000010000010010110000100000010010010100110101001101 Z
#65
b0 X
b110011 %
b110011 T
b1 &
b1 S
12
#70
02
#75
b1 X
12
#80
02
b1110000 3
b1110000 >
1Y
b100110101001111010101100010000001000010001011000010000001000011 Z
#85
b0 X
1/
12
#90
02
#95
b1 X
0/
12
#100
02
b1000000 3
b1000000 >
0Y
b10010000100110001010100001000000100100101101110011100110111010001110010011101010110001101110100011010010110111101101110 Z
#105
b10 .
b10 N
b0 X
b10001 0
b10001 M
1*
1#
b10001 +
b10001 P
12
#110
02
#115
b1 X
0#
b1 .
b1 N
12
#120
02
b10100000101001001001110010101000010000001000001 Z
